cafspy/__init__.py
cafspy/module.py
cafspy-0.0.1.dist-info/METADATA
cafspy-0.0.1.dist-info/WHEEL
cafspy-0.0.1.dist-info/licenses/LICENSE
cafspy-0.0.1.dist-info/licenses/NOTICE.md
cafspy-0.0.1.dist-info/RECORD
