Metadata-Version: 2.4
Name: cafspy
Version: 0.0.1
Summary: A small example package
Project-URL: Homepage, https://github.com/yourusername/my_package
Project-URL: Bug Tracker, https://github.com/yourusername/my_package/issues
Author-email: Your Name <you@example.com>, Your Name <you@example.com>, Your Name <you@example.com>
License-File: LICENSE
License-File: NOTICE.md
Classifier: License :: OSI Approved :: MIT License
Classifier: Operating System :: OS Independent
Classifier: Programming Language :: Python :: 3
Requires-Python: >=3.9
Requires-Dist: numpy>=2.3.0
Requires-Dist: pandas>=2.3.0
Requires-Dist: scikit-learn>=1.7.0
Requires-Dist: testflows-combinatorics
